[1,["9e/iAXHzxFmoTNxCcMWRWq"],0,[["sp.SkeletonData",["_name","_atlasText","textureNames","_skeletonJson","textures"],-1,3]],[[0,0,1,2,3,4,5]],[[0,"room_5_15","\nroom_5_15.png\nsize: 2003,763\nformat: RGBA8888\nfilter: Linear,Linear\nrepeat: none\na\n  rotate: true\n  xy: 1402, 11\n  size: 750, 172\n  orig: 752, 177\n  offset: 1, 1\n  index: -1\nas\n  rotate: true\n  xy: 1857, 14\n  size: 747, 144\n  orig: 750, 161\n  offset: 1, 16\n  index: -1\nb\n  rotate: true\n  xy: 1739, 11\n  size: 750, 116\n  orig: 752, 127\n  offset: 1, 4\n  index: -1\nc\n  rotate: true\n  xy: 1576, 11\n  size: 750, 161\n  orig: 752, 163\n  offset: 1, 1\n  index: -1\nd\n  rotate: true\n  xy: 2, 196\n  size: 565, 707\n  orig: 567, 709\n  offset: 1, 1\n  index: -1\nd1\n  rotate: false\n  xy: 330, 109\n  size: 104, 48\n  orig: 106, 50\n  offset: 1, 1\n  index: -1\nd2\n  rotate: false\n  xy: 436, 74\n  size: 83, 48\n  orig: 85, 50\n  offset: 1, 1\n  index: -1\nd3\n  rotate: true\n  xy: 663, 75\n  size: 82, 46\n  orig: 84, 48\n  offset: 1, 1\n  index: -1\nd4\n  rotate: true\n  xy: 521, 53\n  size: 69, 48\n  orig: 71, 50\n  offset: 1, 1\n  index: -1\ne\n  rotate: true\n  xy: 711, 213\n  size: 548, 689\n  orig: 553, 692\n  offset: 1, 1\n  index: -1\nf1\n  rotate: true\n  xy: 2, 159\n  size: 35, 705\n  orig: 37, 707\n  offset: 1, 1\n  index: -1\nf2\n  rotate: true\n  xy: 711, 5\n  size: 206, 565\n  orig: 210, 567\n  offset: 3, 1\n  index: -1\ng1\n  rotate: true\n  xy: 436, 124\n  size: 33, 182\n  orig: 35, 187\n  offset: 1, 4\n  index: -1\ng2\n  rotate: false\n  xy: 2, 7\n  size: 204, 150\n  orig: 206, 156\n  offset: 1, 4\n  index: -1\nguang\n  rotate: false\n  xy: 620, 2\n  size: 41, 155\n  orig: 47, 159\n  offset: 4, 3\n  index: -1\ns\n  rotate: false\n  xy: 1278, 87\n  size: 106, 124\n  orig: 108, 126\n  offset: 1, 1\n  index: -1\ns2\n  rotate: false\n  xy: 1278, 3\n  size: 87, 82\n  orig: 87, 82\n  offset: 0, 0\n  index: -1\nzhuan\n  rotate: false\n  xy: 208, 66\n  size: 120, 91\n  orig: 120, 92\n  offset: 0, 1\n  index: -1\n",["room_5_15.png"],{"skeleton":{"hash":"qYR+WGcJtuX43pV3WzdHodkKFVg","spine":"3.8.99","x":-375,"y":-455,"width":752,"height":944},"bones":[{"name":"root"},{"name":"a","parent":"root","x":-43.1,"y":403.28},{"name":"d","parent":"root","x":-76.19,"y":99.78},{"name":"guang","parent":"root","x":-370.67,"y":66.81,"scaleX":1.882,"scaleY":4.9312,"shearY":2.37},{"name":"z1","parent":"root","x":212.88,"y":-204.43},{"name":"z2","parent":"root","x":69.2,"y":-163.38},{"name":"z3","parent":"root","x":234.34,"y":-77.54},{"name":"s2","parent":"root","x":28.7,"y":-377.38},{"name":"s","parent":"root","length":101.86,"rotation":81.57,"x":2.58,"y":-407.23}],"slots":[{"name":"d","bone":"d","attachment":"d"},{"name":"d4","bone":"d","color":"ffffff00","attachment":"d4"},{"name":"d3","bone":"d","color":"ffffff00","attachment":"d3"},{"name":"d2","bone":"d","color":"ffffff00","attachment":"d2"},{"name":"d1","bone":"d","color":"ffffff00","attachment":"d1"},{"name":"f2","bone":"root","color":"ffffff00","attachment":"f2"},{"name":"f1","bone":"root","color":"ffffff00","attachment":"f1"},{"name":"g2","bone":"root","color":"ffffff00","attachment":"g2"},{"name":"g1","bone":"root","color":"ffffff00","attachment":"g1"},{"name":"e","bone":"root","color":"ffffff00","attachment":"e"},{"name":"c","bone":"root","attachment":"c"},{"name":"b","bone":"root","attachment":"b"},{"name":"s2","bone":"s2","color":"ffffff00","attachment":"s2"},{"name":"s","bone":"s","color":"ffffff00","attachment":"s"},{"name":"guang_m","bone":"root","attachment":"guang_m"},{"name":"guang","bone":"guang","color":"ffab49ff","attachment":"guang","blend":"additive"},{"name":"as","bone":"a","attachment":"as"},{"name":"a","bone":"a","attachment":"a"},{"name":"zhuan","bone":"z1","color":"ffffff00","attachment":"zhuan"},{"name":"zhuan2","bone":"z2","color":"ffffff00","attachment":"zhuan"},{"name":"zhuan3","bone":"z3","color":"ffffff00","attachment":"zhuan"}],"skins":[{"name":"default","attachments":{"a":{"a":{"x":44.1,"y":-2.78,"width":752,"height":177}},"as":{"as":{"x":43.1,"y":-55.78,"width":750,"height":161}},"b":{"b":{"x":1,"y":-240.5,"width":752,"height":127}},"c":{"c":{"x":1,"y":392.5,"width":752,"height":163}},"d":{"d":{"x":-11.31,"y":-16.28,"width":567,"height":709}},"d1":{"d1":{"x":-86.81,"y":4.22,"width":106,"height":50}},"d2":{"d2":{"x":61.69,"y":38.22,"width":85,"height":50}},"d3":{"d3":{"x":-15.81,"y":-43.78,"width":84,"height":48}},"d4":{"d4":{"x":17.69,"y":82.22,"width":71,"height":50}},"e":{"e":{"x":-86.5,"y":79,"width":553,"height":692}},"f1":{"f1":{"x":-356.5,"y":78.5,"width":37,"height":707}},"f2":{"f2":{"x":272,"y":59.5,"width":210,"height":567}},"g1":{"g1":{"x":-357.5,"y":4.5,"width":35,"height":187}},"g2":{"g2":{"x":274,"width":206,"height":156}},"guang":{"guang":{"x":-16.08,"y":1.06,"width":47,"height":159}},"guang_m":{"guang_m":{"type":"clipping","end":"guang","vertexCount":4,"vertices":[-369.48,422.43,193.99,340.16,183.07,-215.3,-339.63,-260.44]}},"s":{"s":{"x":55.47,"y":-4.34,"rotation":-81.57,"width":108,"height":126}},"s2":{"s2":{"type":"mesh","hull":4,"uvs":[1,1,0,1,0,0,1,0],"triangles":[1,2,3,1,3,0],"vertices":[42.3,-77.62,-44.7,-77.62,-44.7,4.38,42.3,4.38]}},"zhuan":{"zhuan":{"type":"mesh","hull":6,"uvs":[0.99643,0.607,0.46253,0.98837,0.01783,0.97209,0.00357,0.30228,0.58736,0,0.98752,0.01163,0.46431,0.32554],"triangles":[6,3,4,6,4,5,6,5,0,2,3,6,1,2,6,1,6,0],"vertices":[51.96,-12.95,-12.11,-48.03,-65.47,-46.54,-67.19,15.09,2.87,42.9,50.89,41.83,-11.9,12.95]}},"zhuan2":{"zhuan":{"type":"mesh","hull":6,"uvs":[0.99643,0.607,0.46253,0.98837,0.01783,0.97209,0.00357,0.30228,0.58736,0,0.98752,0.01163,0.46431,0.32554],"triangles":[6,3,4,6,4,5,6,5,0,2,3,6,1,2,6,1,6,0],"vertices":[51.96,-12.95,-12.11,-48.03,-65.47,-46.54,-67.19,15.09,2.87,42.9,50.89,41.83,-11.9,12.95]}},"zhuan3":{"zhuan":{"type":"mesh","hull":6,"uvs":[0.99643,0.607,0.46253,0.98837,0.01783,0.97209,0.00357,0.30228,0.58736,0,0.98752,0.01163,0.46431,0.32554],"triangles":[6,3,4,6,4,5,6,5,0,2,3,6,1,2,6,1,6,0],"vertices":[51.96,-12.95,-12.11,-48.03,-65.47,-46.54,-67.19,15.09,2.87,42.9,50.89,41.83,-11.9,12.95]}}}}],"animations":{"loop_a":{},"loop_b":{"slots":{"a":{"color":[{"color":"ffffff00"}]},"as":{"color":[{"color":"ffffff00"}]},"d1":{"color":[{"color":"ffffffff"}]},"d2":{"color":[{"color":"ffffffff"}]},"d3":{"color":[{"color":"ffffffff"}]},"d4":{"color":[{"color":"ffffffff"}]},"e":{"color":[{"color":"ffffffff"}]}},"bones":{"a":{"translate":[{"x":104.38,"y":133.85}],"scale":[{"x":1.435,"y":1.435}],"shear":[{"x":-0.59}]},"z1":{"translate":[{"x":-218.77,"y":345.15}]},"z2":{"translate":[{"x":-225.07,"y":265.35}]},"z3":{"translate":[{"x":-323.21,"y":140.77}]},"guang":{"translate":[{"x":679.89}],"shear":[{"y":-4.81}]}},"deform":{"default":{"zhuan":{"zhuan":[{"vertices":[-22.29499,-13.19502,-31.85001,25.02504,19.11002,25.93498,20.47501,2.73,15.015,-28.20998,-20.92998,-28.21002,-31.85,3.18498]}]},"zhuan2":{"zhuan":[{"vertices":[-10.24998,-8.60999,-41.99498,27.38998,8.86505,28.19499,9.40999,9.40999,20.91,-21.72996,-10.65999,-21.31998,-43.55493,12.76494]}]},"zhuan3":{"zhuan":[{"vertices":[-17.01997,-14.80003,-28.48999,21.08996,22.93998,20.71997,24.41998,-1.11002,24.04998,-30.33998,-17.01997,-29.60003,-28.48999,1.84999]}]}}}},"loop_c":{"slots":{"a":{"color":[{"color":"ffffff00"}]},"as":{"color":[{"color":"ffffff00"}]},"d1":{"color":[{"color":"ffffffff"}]},"d2":{"color":[{"color":"ffffffff"}]},"d3":{"color":[{"color":"ffffffff"}]},"d4":{"color":[{"color":"ffffffff"}]},"e":{"color":[{"color":"ffffffff"}]},"f1":{"color":[{"color":"ffffffff"}]},"f2":{"color":[{"color":"ffffffff"}]},"g1":{"color":[{"color":"ffffffff"}]},"g2":{"color":[{"color":"ffffffff"}]}},"bones":{"a":{"translate":[{"x":104.38,"y":133.85}],"scale":[{"x":1.435,"y":1.435}],"shear":[{"x":-0.59}]},"z1":{"translate":[{"x":-218.77,"y":345.15}]},"z2":{"translate":[{"x":-225.07,"y":265.35}]},"z3":{"translate":[{"x":-323.21,"y":140.77}]},"guang":{"translate":[{"x":679.89}],"shear":[{"y":-4.81}]},"root":{"translate":[{"x":2.13}]},"s":{"rotate":[{"angle":21.23}],"translate":[{"x":470.18,"y":142.13}],"scale":[{"x":0.8,"y":0.8}],"shear":[{"x":32.07,"y":34.08}]},"s2":{"translate":[{"x":208.8,"y":193.01}],"scale":[{"y":-6.2}]}},"deform":{"default":{"s2":{"s2":[{"vertices":[140.07652,17.64641,126.00403,17.43365,126.76025,-4.78839,143.19992,-6.77214]}]},"zhuan":{"zhuan":[{"vertices":[-22.29499,-13.19502,-31.85001,25.02504,19.11002,25.93498,20.47501,2.73,15.015,-28.20998,-20.92998,-28.21002,-31.85,3.18498]}]},"zhuan2":{"zhuan":[{"vertices":[-10.24998,-8.60999,-41.99498,27.38998,8.86505,28.19499,9.40999,9.40999,20.91,-21.72996,-10.65999,-21.31998,-43.55493,12.76494]}]},"zhuan3":{"zhuan":[{"vertices":[-17.01997,-14.80003,-28.48999,21.08996,22.93998,20.71997,24.41998,-1.11002,24.04998,-30.33998,-17.01997,-29.60003,-28.48999,1.84999]}]}}}},"trigger":{"slots":{"a":{"color":[{"time":2.5,"color":"ffffffff"},{"time":2.8333,"color":"ffffff00"}]},"as":{"color":[{"time":0.8333,"color":"ffffffff"},{"time":1,"color":"ffffff00"}]},"d1":{"color":[{"time":3.8333,"color":"ffffff00"},{"time":4,"color":"ffffffff"}]},"d2":{"color":[{"time":3.5,"color":"ffffff00"},{"time":3.6667,"color":"ffffffff"}]},"d3":{"color":[{"time":4.3333,"color":"ffffff00"},{"time":4.5,"color":"ffffffff"}]},"d4":{"color":[{"time":3.5,"color":"ffffff00"},{"time":3.6667,"color":"ffffffff"}]},"e":{"color":[{"time":5.3333,"color":"ffffff00"},{"time":5.8333,"color":"ffffffff"}]},"guang":{"color":[{"time":5.6667,"color":"ffab49ff"},{"time":6,"color":"ffab4900"}]},"zhuan":{"color":[{"time":2.6667,"color":"ffffff00"},{"time":3,"color":"ffffffff","curve":"stepped"},{"time":3.5,"color":"ffffffff"},{"time":3.6667,"color":"ffffff00"}]},"zhuan2":{"color":[{"time":3,"color":"ffffff00"},{"time":3.3333,"color":"ffffffff","curve":"stepped"},{"time":3.8333,"color":"ffffffff"},{"time":4,"color":"ffffff00"}]},"zhuan3":{"color":[{"time":3.5,"color":"ffffff00"},{"time":3.8333,"color":"ffffffff","curve":"stepped"},{"time":4.3333,"color":"ffffffff"},{"time":4.5,"color":"ffffff00"}]}},"bones":{"a":{"translate":[{"time":0.6667},{"time":0.8333,"y":8.84,"curve":"stepped"},{"time":1,"y":8.84},{"time":1.3333,"x":9.07,"y":88.7},{"time":1.6667,"x":15.7,"y":115.22},{"time":2.1667,"x":25.79,"y":-188.85},{"time":2.8333,"x":104.38,"y":133.85}],"scale":[{"time":1},{"time":1.3333,"x":1.136,"y":1.136,"curve":"stepped"},{"time":1.6667,"x":1.136,"y":1.136},{"time":2.8333,"x":1.435,"y":1.435}],"shear":[{},{"time":0.1667,"x":2.09},{"time":0.3333,"x":-0.59},{"time":0.5,"x":2.09},{"time":0.6667,"x":-0.59},{"time":0.8333,"x":2.09},{"time":1,"x":-0.59}]},"z1":{"rotate":[{"time":2.6667,"angle":32.73},{"time":3.5}],"translate":[{"time":2.6667},{"time":3.5,"x":-218.77,"y":345.15}]},"z2":{"rotate":[{"time":3,"angle":32.73},{"time":3.8333}],"translate":[{"time":3},{"time":3.8333,"x":-225.07,"y":265.35}]},"z3":{"rotate":[{"time":3.5,"angle":32.73},{"time":4.3333}],"translate":[{"time":3.5},{"time":4.3333,"x":-323.21,"y":140.77}]},"guang":{"translate":[{"time":4.6667},{"time":5.6667,"x":679.89}],"shear":[{"time":4.6667},{"time":5.6667,"y":-4.81}]}},"deform":{"default":{"zhuan":{"zhuan":[{"time":2.6667},{"time":3.5,"vertices":[-22.29499,-13.19502,-31.85001,25.02504,19.11002,25.93498,20.47501,2.73,15.015,-28.20998,-20.92998,-28.21002,-31.85,3.18498]}]},"zhuan2":{"zhuan":[{"time":3},{"time":3.8333,"vertices":[-10.24998,-8.60999,-41.99498,27.38998,8.86505,28.19499,9.40999,9.40999,20.91,-21.72996,-10.65999,-21.31998,-43.55493,12.76494]}]},"zhuan3":{"zhuan":[{"time":3.5},{"time":4.3333,"vertices":[-17.01997,-14.80003,-28.48999,21.08996,22.93998,20.71997,24.41998,-1.11002,24.04998,-30.33998,-17.01997,-29.60003,-28.48999,1.84999]}]}}}},"trigger2":{"slots":{"a":{"color":[{"color":"ffffff00"}]},"as":{"color":[{"color":"ffffff00"}]},"d1":{"color":[{"color":"ffffffff"}]},"d2":{"color":[{"color":"ffffffff"}]},"d3":{"color":[{"color":"ffffffff"}]},"d4":{"color":[{"color":"ffffffff"}]},"e":{"color":[{"color":"ffffffff"}]},"f1":{"color":[{"time":1.3333,"color":"ffffff00"},{"time":2.3333,"color":"ffffffff"}]},"f2":{"color":[{"time":3.1667,"color":"ffffff00"},{"time":6,"color":"ffffffff"}]},"g1":{"color":[{"time":2.3333,"color":"ffffff00"},{"time":2.8333,"color":"ffffffff"}]},"g2":{"color":[{"time":6.5,"color":"ffffff00"},{"time":7,"color":"ffffffff"}]},"s":{"color":[{"color":"ffffff00"},{"time":0.3333,"color":"ffffffff","curve":"stepped"},{"time":6.1667,"color":"ffffffff"},{"time":6.5,"color":"ffffff00"}]},"s2":{"color":[{"time":1,"color":"ffffff00"},{"time":1.1333,"color":"ffffffff","curve":"stepped"},{"time":1.6667,"color":"ffffffff"},{"time":2,"color":"ffffff00","curve":"stepped"},{"time":3.1667,"color":"ffffff00"},{"time":3.3,"color":"ffffffff","curve":"stepped"},{"time":4,"color":"ffffffff"},{"time":4.3333,"color":"ffffff00","curve":"stepped"},{"time":5.1667,"color":"ffffff00"},{"time":5.3,"color":"ffffffff","curve":"stepped"},{"time":6,"color":"ffffffff"},{"time":6.3333,"color":"ffffff00"}]}},"bones":{"a":{"translate":[{"x":104.38,"y":133.85}],"scale":[{"x":1.435,"y":1.435}],"shear":[{"x":-0.59}]},"z1":{"translate":[{"x":-218.77,"y":345.15}]},"z2":{"translate":[{"x":-225.07,"y":265.35}]},"z3":{"translate":[{"x":-323.21,"y":140.77}]},"guang":{"translate":[{"x":679.89}],"shear":[{"y":-4.81}]},"root":{"translate":[{"x":2.13}]},"s":{"rotate":[{"angle":40.24},{"time":0.6667,"angle":-11.58,"curve":"stepped"},{"time":6.1667,"angle":-11.58},{"time":6.5,"angle":21.23}],"translate":[{},{"time":0.6667,"x":-391.66,"y":101.14},{"time":1,"x":-381.98,"y":90.38},{"time":1.6667,"x":-417.49,"y":683.26,"curve":"stepped"},{"time":1.8333,"x":-417.49,"y":683.26},{"time":2.5,"x":54.88,"y":703.7},{"time":3.1667,"x":251.78,"y":638.07},{"time":4,"x":247.48,"y":146.34,"curve":"stepped"},{"time":4.1667,"x":247.48,"y":146.34},{"time":5,"x":309.89,"y":619.78,"curve":"stepped"},{"time":5.1667,"x":309.89,"y":619.78},{"time":6,"x":380.9,"y":159.25,"curve":"stepped"},{"time":6.1667,"x":380.9,"y":159.25},{"time":6.5,"x":470.18,"y":142.13}],"scale":[{"x":1.5,"y":1.5},{"time":0.6667,"curve":"stepped"},{"time":1.8333},{"time":2.5,"x":1.2,"y":1.2},{"time":3.1667,"x":0.9,"y":0.9,"curve":"stepped"},{"time":4.1667,"x":0.9,"y":0.9},{"time":6,"x":0.8,"y":0.8}],"shear":[{},{"time":1,"x":27.99,"y":30.17},{"time":1.6667,"x":21.03,"y":14.73,"curve":"stepped"},{"time":3.1667,"x":21.03,"y":14.73},{"time":4,"x":30.05,"y":32.68,"curve":"stepped"},{"time":4.1667,"x":30.05,"y":32.68},{"time":5,"x":7.96,"y":4.09,"curve":"stepped"},{"time":5.1667,"x":7.96,"y":4.09},{"time":6,"x":32.07,"y":34.08}]},"s2":{"translate":[{"time":1,"x":-412.15,"y":144.31},{"time":1.6667,"x":-439.97,"y":734.1,"curve":"stepped"},{"time":2,"x":-439.97,"y":734.1},{"time":3.1667,"x":226.3,"y":685.64},{"time":4,"x":208.8,"y":193.01,"curve":"stepped"},{"time":4.3333,"x":208.8,"y":193.01},{"time":5.1667,"x":226.3,"y":685.64},{"time":6,"x":208.8,"y":193.01}],"scale":[{"time":1},{"time":1.6667,"y":6.216},{"time":2},{"time":3.1667,"y":-1},{"time":4.3333,"y":-6.2},{"time":5.1667,"y":-1},{"time":6.3333,"y":-6.2}]}},"deform":{"default":{"s2":{"s2":[{"time":1,"offset":2,"vertices":[1.392,-16.00803,-4.87201,-11.832]},{"time":1.6667,"vertices":[18.57919,22.8603,0.4949,22.8603,-14.79663,-0.00001,1.64304,-1.98376]},{"time":3.1667,"vertices":[-2.48384,54.95634,-14.55011,45.92933,-14.79663,-0.00001,1.64304,-1.98376]},{"time":4,"curve":"stepped","vertices":[-1.48036,22.43478,-15.55286,22.22203,-14.79663,-0.00001,1.64304,-1.98376]},{"time":4.3333,"vertices":[-1.48036,22.43478,-15.55286,22.22203,-14.79663,-0.00001,1.64304,-1.98376]},{"time":5.1667,"vertices":[84.11186,43.83282,70.03937,43.62007,70.79559,21.39803,87.23526,19.41428]},{"time":6,"vertices":[140.07652,17.64641,126.00403,17.43365,126.76025,-4.78839,143.19992,-6.77214]}]},"zhuan":{"zhuan":[{"vertices":[-22.29499,-13.19502,-31.85001,25.02504,19.11002,25.93498,20.47501,2.73,15.015,-28.20998,-20.92998,-28.21002,-31.85,3.18498]}]},"zhuan2":{"zhuan":[{"vertices":[-10.24998,-8.60999,-41.99498,27.38998,8.86505,28.19499,9.40999,9.40999,20.91,-21.72996,-10.65999,-21.31998,-43.55493,12.76494]}]},"zhuan3":{"zhuan":[{"vertices":[-17.01997,-14.80003,-28.48999,21.08996,22.93998,20.71997,24.41998,-1.11002,24.04998,-30.33998,-17.01997,-29.60003,-28.48999,1.84999]}]}}}}}},[0]]],0,0,[0],[-1],[0]]