[1,["ecpdLyjvZBwrvm+cedCcQy","31YphVJdxCrpcpqgpsxWmC","416BbWValMWqDHW7Nn/Pw9","65d61tx21OLrGBF1hGravS","29ujNOVLxLHIpcSxqF95UM","b0N/HVsH5JwIhh5/LAkZrD","e1qQYblWhCAJdb3UKFLD7m","ec9EslsX1KqY98c/iD7oEe","d697JqGspAY4UjMvCEvP/5","eczZlexVlOkahN3ZMrALEA","b21p7QunVCDZApxr0w0F4t","cbJSqihLhBbotRCv30Saek","95XtyLQJVDxrandrQOUUis"],["node","_spriteFrame","_textureSetter","itemParent","price","discount","giftName","crystal","energy","itemPrefab","root","data"],[["cc.Node",["_name","_components","_prefab","_contentSize","_trs","_children","_parent","_anchorPoint"],2,9,4,5,7,2,1,5],"cc.SpriteFrame",["cc.Node",["_name","_parent","_components","_prefab","_contentSize","_trs","_color","_eulerAngles"],2,1,12,4,5,7,5,5],["cc.Layout",["_N$layoutType","_resize","_N$spacingY","_N$spacingX","node","_layoutSize"],-1,1,5],["cc.PrefabInfo",["fileId","root","asset"],2,1,1],["cc.Sprite",["_type","_sizeMode","node","_materials","_spriteFrame"],1,1,3,6],["cc.Label",["_string","_styleFlags","_N$horizontalAlign","_N$verticalAlign","_fontSize","_lineHeight","node","_materials"],-3,1,3],["cc.Prefab",["_name"],2],["6a07aRuybtIFJ1y7dYv6PFK",["node"],3,1],["048a5aTKbhKxIOZaoZ6MKga",["node","energy","crystal","giftName","discount","price","itemParent","itemPrefab"],3,1,1,1,1,1,1,1,6],["cc.Button",["zoomScale","node","clickEvents"],2,1,9],["cc.ClickEvent",["_componentId","handler","target"],1,1],["cc.LabelOutline",["_width","node","_color"],2,1,5]],[[4,0,1,2,2],[5,2,3,4,1],[12,0,1,2,2],[0,0,6,5,1,2,3,4,2],[2,0,1,2,3,4,5,2],[0,0,6,1,2,3,4,2],[6,0,1,2,3,6,7,5],[6,0,4,5,1,2,3,6,7,7],[5,0,1,2,3,4,3],[2,0,1,2,3,6,4,5,7,2],[3,0,3,4,5,3],[9,0,1,2,3,4,5,6,7,1],[10,0,1,2,2],[11,0,1,2,3],[7,0,2],[0,0,5,1,2,3,4,2],[0,0,6,5,1,2,3,7,4,2],[3,1,0,2,4,5,4],[8,0,1],[4,1,2,1]],[[[{"name":"img_pack_1","rect":[0,0,259,240],"offset":[0,0],"originalSize":[259,240],"capInsets":[0,0,0,0]}],[1],0,[0],[2],[10]],[[{"name":"ico_off_41e816d6-55a9-4c5a-a0c7-5bb367fcfc3d","rect":[0,0,120,121],"offset":[0,0],"originalSize":[120,121],"capInsets":[0,0,0,0]}],[1],0,[0],[2],[11]],[[[14,"shop_tehui"],[15,"gift",[-4,-5,-6,-7],[[17,1,2,12,-2,[5,740,1266]],[18,-3]],[19,-1,0],[5,740,1266],[0,-2605.463,0,0,0,0,1,1,1,1]],[3,"1",1,[-16,-17,-18,-19,-20,-21],[[8,1,0,-8,[22],23],[11,-15,-14,-13,-12,-11,-10,-9,24]],[0,"94DIT8T1dFxKMeLJLNe6+4",1,0],[5,700,360],[0,291,0,0,0,0,1,1,1,1]],[3,"2",1,[-30,-31,-32,-33,-34,-35],[[8,1,0,-22,[42],43],[11,-29,-28,-27,-26,-25,-24,-23,44]],[0,"953Pw8HKVJL5mPYDXbSMsa",1,0],[5,700,360],[0,-81,0,0,0,0,1,1,1,1]],[3,"3",1,[-44,-45,-46,-47,-48,-49],[[8,1,0,-36,[62],63],[11,-43,-42,-41,-40,-39,-38,-37,64]],[0,"33D5rZuUNNLqBF3nQT2mec",1,0],[5,700,360],[0,-453,0,0,0,0,1,1,1,1]],[3,"img_pack_ribbon",2,[-51,-52,-53],[[1,-50,[11],12]],[0,"2deUaXWYpLlbq8Rq0YQFYN",1,0],[5,506,99],[-113.075,-112.082,0,0,0,0,1,1,1,1]],[3,"img_pack_ribbon",3,[-55,-56,-57],[[1,-54,[31],32]],[0,"feadfbyeVItbyKwZ+G/4kK",1,0],[5,506,99],[-113.075,-112.082,0,0,0,0,1,1,1,1]],[3,"img_pack_ribbon",4,[-59,-60,-61],[[1,-58,[51],52]],[0,"18cnBeEz9EYansuXwGLX2U",1,0],[5,506,99],[-113.075,-112.082,0,0,0,0,1,1,1,1]],[16,"img_title",1,[-63,-64],[[1,-62,[3],4]],[0,"059WjTVnlA/5dYHi8GQyIp",1,0],[5,256,150],[0,1,0.5],[0,558,0,0,0,0,1,1,1,1]],[3,"btn_rounded_green",2,[-67],[[8,1,0,-65,[14],15],[12,1.1,-66,[[13,"048a5aTKbhKxIOZaoZ6MKga","onBuyClicked",2]]]],[0,"52T08v9ElBvYJ2LmAXwSXP",1,0],[5,180,70],[243.306,-120.31,0,0,0,0,1,1,1,0]],[3,"btn_rounded_green",3,[-70],[[8,1,0,-68,[34],35],[12,1.1,-69,[[13,"048a5aTKbhKxIOZaoZ6MKga","onBuyClicked",3]]]],[0,"eaeygqHtJN57DJ+83I7qIN",1,0],[5,180,70],[243.306,-120.31,0,0,0,0,1,1,1,0]],[3,"btn_rounded_green",4,[-73],[[8,1,0,-71,[54],55],[12,1.1,-72,[[13,"048a5aTKbhKxIOZaoZ6MKga","onBuyClicked",4]]]],[0,"bcnQ8B2OdIAKfIfPQKRbgr",1,0],[5,180,70],[243.306,-120.31,0,0,0,0,1,1,1,0]],[5,"title",8,[[7,"特惠礼包",48,48,1,1,1,-74,[2]],[2,4,-75,[4,1291845632]]],[0,"d083gSailHw6UIto1mqfjl",1,0],[5,200,68.47999999999999],[0,24.037,0,0,0,0,1,1,1,1]],[4,"label",5,[[-76,[2,4,-77,[4,1275068416]]],1,4],[0,"7apWzvDJdA5YIIhbAtkG3t",1,0],[5,248,58.4],[-86.925,-3.968,0,0,0,0,1,1,1,1]],[9,"label",5,[[-78,[2,3,-79,[4,4289206640]]],1,4],[0,"ddAFIj3z1DBpdSictkB9Hi",1,0],[4,4284936447],[5,64.39,58.92],[100.826,18.594,0,0,0,0.04360195067784048,0.9990489827316212,1,1,1],[1,0,0,4.998]],[4,"label",9,[[-80,[2,3,-81,[4,1275068416]]],1,4],[0,"ddPYykWatNprDaMO0JfCOj",1,0],[5,102.72,43.8],[0,2.26,0,0,0,0,1,1,1,1]],[3,"ico_crystal",2,[-83],[[1,-82,[17],18]],[0,"20eAlPWbJJpIyEVTcjWQG1",1,0],[5,54,52],[-7,129,0,0,0,0,1,1,1,1]],[4,"label",16,[[-84,[2,4,-85,[4,4290529273]]],1,4],[0,"d7v1JSrJpLHIOLnxKMMkH4",1,0],[5,74.74,58.4],[77.093,2,0,0,0,0,1,1,1,1]],[3,"ico_energy",2,[-87],[[1,-86,[20],21]],[0,"f2w/Hg2Z5GjIQD5bG2N8L4",1,0],[5,50,62],[167,129,0,0,0,0,1,1,1,1]],[4,"label",18,[[-88,[2,4,-89,[4,4290529273]]],1,4],[0,"d0sRt6DJ1B/qwZX9BMp2Ib",1,0],[5,74.74,58.4],[75.005,3,0,0,0,0,1,1,1,1]],[5,"award",2,[[10,1,5,-90,[5,450,140]]],[0,"5aWeZBWfdO+oYgJnn9w5lY",1,0],[5,450,140],[130.226,34.018,0,0,0,0,1,1,1,1]],[4,"label",6,[[-91,[2,4,-92,[4,1275068416]]],1,4],[0,"33tj3ZQs9Nsr/nAXqZWVyR",1,0],[5,248,58.4],[-86.925,-3.968,0,0,0,0,1,1,1,1]],[9,"label",6,[[-93,[2,3,-94,[4,4289206640]]],1,4],[0,"04/7aarjpBXL6L82PYLqMg",1,0],[4,4284936447],[5,64.39,58.92],[100.826,18.594,0,0,0,0.04360195067784048,0.9990489827316212,1,1,1],[1,0,0,4.998]],[4,"label",10,[[-95,[2,3,-96,[4,1275068416]]],1,4],[0,"46e5OOyT1PdqTiS/enDXZP",1,0],[5,102.72,43.8],[0,2.26,0,0,0,0,1,1,1,1]],[3,"ico_crystal",3,[-98],[[1,-97,[37],38]],[0,"f2PYepDbdBy7//iHCLAA8w",1,0],[5,54,52],[-7,129,0,0,0,0,1,1,1,1]],[4,"label",24,[[-99,[2,4,-100,[4,4290529273]]],1,4],[0,"7dQQT1V2VBsqUoXptqu3FB",1,0],[5,74.74,58.4],[77.093,2,0,0,0,0,1,1,1,1]],[3,"ico_energy",3,[-102],[[1,-101,[40],41]],[0,"16zvea1mhPsrYVKIOnc/E3",1,0],[5,50,62],[167,129,0,0,0,0,1,1,1,1]],[4,"label",26,[[-103,[2,4,-104,[4,4290529273]]],1,4],[0,"a0M6dvuZ5DYbHwbDpKjF9y",1,0],[5,74.74,58.4],[75.005,3,0,0,0,0,1,1,1,1]],[5,"award",3,[[10,1,5,-105,[5,450,140]]],[0,"9e4eYcRMFIVrLuxjVimguF",1,0],[5,450,140],[130.226,34.018,0,0,0,0,1,1,1,1]],[4,"label",7,[[-106,[2,4,-107,[4,1275068416]]],1,4],[0,"42Rk7hVwBFCZZaIJBv1kC3",1,0],[5,248,58.4],[-86.925,-3.968,0,0,0,0,1,1,1,1]],[9,"label",7,[[-108,[2,3,-109,[4,4289206640]]],1,4],[0,"a55fCQpM1FrJTwWULrtaV9",1,0],[4,4284936447],[5,64.39,58.92],[100.826,18.594,0,0,0,0.04360195067784048,0.9990489827316212,1,1,1],[1,0,0,4.998]],[4,"label",11,[[-110,[2,3,-111,[4,1275068416]]],1,4],[0,"25yeng3MJBmLYF7kYarH0Z",1,0],[5,102.72,43.8],[0,2.26,0,0,0,0,1,1,1,1]],[3,"ico_crystal",4,[-113],[[1,-112,[57],58]],[0,"3evdrOkLlNmItqIddzHfp0",1,0],[5,54,52],[-7,129,0,0,0,0,1,1,1,1]],[4,"label",32,[[-114,[2,4,-115,[4,4290529273]]],1,4],[0,"1cE419ry5LHa1bh0M7pIf0",1,0],[5,74.74,58.4],[77.093,2,0,0,0,0,1,1,1,1]],[3,"ico_energy",4,[-117],[[1,-116,[60],61]],[0,"83qXMgLlNItKf3JD756u7h",1,0],[5,50,62],[167,129,0,0,0,0,1,1,1,1]],[4,"label",34,[[-118,[2,4,-119,[4,4290529273]]],1,4],[0,"9488FTcoFAZqaUvlSPml/v",1,0],[5,74.74,58.4],[75.005,3,0,0,0,0,1,1,1,1]],[5,"award",4,[[10,1,5,-120,[5,450,140]]],[0,"f5YPc008xITZU4bpibMXR2",1,0],[5,450,140],[130.226,34.018,0,0,0,0,1,1,1,1]],[5,"img_title",8,[[1,-121,[0],1]],[0,"4dWhjYKv5Gmr85NG6gxLUQ",1,0],[5,256,150],[128.017,0,0,0,0,0,1,-1,1,-1]],[5,"img_pack_1",2,[[1,-122,[5],6]],[0,"99zdQ62sNOmLM6fXlKV5fM",1,0],[5,259,240],[-228.972,30.257,0,0,0,0,1,1,1,1]],[5,"ico_off",5,[[1,-123,[7],8]],[0,"08rvszA3JOS6gKdH0fvu67",1,0],[5,120,121],[102.67,-0.988,0,0,0,0,1,1,1,1]],[6,"礼包礼包礼包",1,1,1,13,[9]],[7,"8.4",42,42,1,1,1,14,[10]],[7,"￥ 0.00",30,30,1,1,1,15,[13]],[6,"000",1,1,1,17,[16]],[6,"000",1,1,1,19,[19]],[5,"img_pack_1",3,[[1,-124,[25],26]],[0,"01wTy0so5O4Zx041vVbqiB",1,0],[5,259,240],[-228.972,30.257,0,0,0,0,1,1,1,1]],[5,"ico_off",6,[[1,-125,[27],28]],[0,"c8WuKvx4NCQYZz00QTBJzZ",1,0],[5,120,121],[102.67,-0.988,0,0,0,0,1,1,1,1]],[6,"礼包礼包礼包",1,1,1,21,[29]],[7,"8.4",42,42,1,1,1,22,[30]],[7,"￥ 0.00",30,30,1,1,1,23,[33]],[6,"000",1,1,1,25,[36]],[6,"000",1,1,1,27,[39]],[5,"img_pack_1",4,[[1,-126,[45],46]],[0,"f27x2GIwpEj5YYoI6BjyrZ",1,0],[5,259,240],[-228.972,30.257,0,0,0,0,1,1,1,1]],[5,"ico_off",7,[[1,-127,[47],48]],[0,"8eE5EIoj5EBIVNpgXraPez",1,0],[5,120,121],[102.67,-0.988,0,0,0,0,1,1,1,1]],[6,"礼包礼包礼包",1,1,1,29,[49]],[7,"8.4",42,42,1,1,1,30,[50]],[7,"￥ 0.00",30,30,1,1,1,31,[53]],[6,"000",1,1,1,33,[56]],[6,"000",1,1,1,35,[59]]],0,[0,10,1,0,0,1,0,0,1,0,-1,8,0,-2,2,0,-3,3,0,-4,4,0,0,2,0,3,20,0,4,42,0,5,41,0,6,40,0,7,43,0,8,44,0,0,2,0,-1,38,0,-2,5,0,-3,9,0,-4,16,0,-5,18,0,-6,20,0,0,3,0,3,28,0,4,49,0,5,48,0,6,47,0,7,50,0,8,51,0,0,3,0,-1,45,0,-2,6,0,-3,10,0,-4,24,0,-5,26,0,-6,28,0,0,4,0,3,36,0,4,56,0,5,55,0,6,54,0,7,57,0,8,58,0,0,4,0,-1,52,0,-2,7,0,-3,11,0,-4,32,0,-5,34,0,-6,36,0,0,5,0,-1,39,0,-2,13,0,-3,14,0,0,6,0,-1,46,0,-2,21,0,-3,22,0,0,7,0,-1,53,0,-2,29,0,-3,30,0,0,8,0,-1,37,0,-2,12,0,0,9,0,0,9,0,-1,15,0,0,10,0,0,10,0,-1,23,0,0,11,0,0,11,0,-1,31,0,0,12,0,0,12,0,-1,40,0,0,13,0,-1,41,0,0,14,0,-1,42,0,0,15,0,0,16,0,-1,17,0,-1,43,0,0,17,0,0,18,0,-1,19,0,-1,44,0,0,19,0,0,20,0,-1,47,0,0,21,0,-1,48,0,0,22,0,-1,49,0,0,23,0,0,24,0,-1,25,0,-1,50,0,0,25,0,0,26,0,-1,27,0,-1,51,0,0,27,0,0,28,0,-1,54,0,0,29,0,-1,55,0,0,30,0,-1,56,0,0,31,0,0,32,0,-1,33,0,-1,57,0,0,33,0,0,34,0,-1,35,0,-1,58,0,0,35,0,0,36,0,0,37,0,0,38,0,0,39,0,0,45,0,0,46,0,0,52,0,0,53,0,11,1,127],[0,0,0,0,0,0,0,0,0,0,0,0,0,0,0,0,0,0,0,0,0,0,0,0,0,0,0,0,0,0,0,0,0,0,0,0,0,0,0,0,0,0,0,0,0,0,0,0,0,0,0,0,0,0,0,0,0,0,0,0,0,0,0,0,0],[-1,1,-1,-1,1,-1,1,-1,1,-1,-1,-1,1,-1,-1,1,-1,-1,1,-1,-1,1,-1,1,9,-1,1,-1,1,-1,-1,-1,1,-1,-1,1,-1,-1,1,-1,-1,1,-1,1,9,-1,1,-1,1,-1,-1,-1,1,-1,-1,1,-1,-1,1,-1,-1,1,-1,1,9],[0,9,0,0,9,0,1,0,2,0,0,0,3,0,0,4,0,0,5,0,0,6,0,7,8,0,1,0,2,0,0,0,3,0,0,4,0,0,5,0,0,6,0,7,8,0,1,0,2,0,0,0,3,0,0,4,0,0,5,0,0,6,0,7,8]],[[{"name":"img_pack_ribbon","rect":[0,0,506,99],"offset":[0,0],"originalSize":[506,99],"capInsets":[0,0,0,0]}],[1],0,[0],[2],[12]]]]